{
  "routes": [
    {
      "method": "GET",
      "path": "/shops",
      "handler": "shop.find",
      "config": {
        "policies": []
      }
    },
    {
      "method": "GET",
      "path": "/shops/count",
      "handler": "shop.count",
      "config": {
        "policies": []
      }
    },
    {
      "method": "GET",
      "path": "/shops/:id",
      "handler": "shop.findOne",
      "config": {
        "policies": []
      }
    },
    {
      "method": "POST",
      "path": "/shops",
      "handler": "shop.create",
      "config": {
        "policies": []
      }
    },
    {
      "method": "PUT",
      "path": "/shops/:id",
      "handler": "shop.update",
      "config": {
        "policies": []
      }
    },
    {
      "method": "DELETE",
      "path": "/shops/:id",
      "handler": "shop.delete",
      "config": {
        "policies": []
      }
    }
  ]
}
