[
  {
    "id": 2,
    "username": "testwebuser",
    "email": null,
    "resetPassowrdToken": null,
    "provider": null,
    "created_at": "2021-01-26T10:40:48.013Z",
    "updated_at": "2021-01-26T10:40:48.023Z",
    "confirmed": null,
    "blocked": null,
    "web_role": null,
    "resetPassowordToken": null,
    "resetPasswordToken": null,
    "test": null
  },
  {
    "id": 3,
    "username": "newPoffuser",
    "email": null,
    "resetPassowrdToken": null,
    "provider": null,
    "created_at": "2021-01-26T10:43:15.406Z",
    "updated_at": "2021-01-26T10:43:15.421Z",
    "confirmed": null,
    "blocked": null,
    "web_role": null,
    "resetPassowordToken": null,
    "resetPasswordToken": null,
    "test": null
  }
]